Nifty4NIFS-1.0b5.data/scripts/runNifty
Nifty4NIFS-1.0b5.dist-info/DESCRIPTION.rst
Nifty4NIFS-1.0b5.dist-info/METADATA
Nifty4NIFS-1.0b5.dist-info/RECORD
Nifty4NIFS-1.0b5.dist-info/WHEEL
Nifty4NIFS-1.0b5.dist-info/metadata.json
Nifty4NIFS-1.0b5.dist-info/top_level.txt
nifty/__init__.py
nifty/pipeline/__init__.py
nifty/pipeline/nifsLowMemoryPipeline.py
nifty/pipeline/nifsPipeline.py
nifty/pipeline/nifsUtils.py
nifty/pipeline/configobj/__init__.py
nifty/pipeline/configobj/configobj.py
nifty/pipeline/downloadFromGeminiPublicArchive/__init__.py
nifty/pipeline/downloadFromGeminiPublicArchive/ndmapperDownloader.py
nifty/pipeline/objectoriented/OOnifsBaseline.py
nifty/pipeline/objectoriented/__init__.py
nifty/pipeline/objectoriented/getConfig.py
nifty/pipeline/objectoriented/routine.py
nifty/pipeline/objectoriented/step.py
nifty/pipeline/objectoriented/subroutine.py
nifty/pipeline/steps/__init__.py
nifty/pipeline/steps/nifsBaselineCalibration.py
nifty/pipeline/steps/nifsFluxCalibrate.py
nifty/pipeline/steps/nifsMerge.py
nifty/pipeline/steps/nifsReduce.py
nifty/pipeline/steps/nifsSort.py
nifty/pipeline/steps/nifsTelluric.py
nifty/pipeline/steps/routines/__init__.py
nifty/pipeline/steps/routines/nifsMakeTelluric.py
nifty/recipes/__init__.py
nifty/recipes/defaultConfig.cfg
nifty/runtimeData/__init__.py
nifty/runtimeData/config.cfg
nifty/runtimeData/h_ar.dat
nifty/runtimeData/j_ar.dat
nifty/runtimeData/k_ar.dat
nifty/runtimeData/new_starstemp.txt
nifty/runtimeData/vega_ext.fits
