Metadata-Version: 2.0
Name: Nifty4NIFS
Version: 1.0b5
Summary: The Gemini NIFS data reduction pipeline.
Home-page: http://www.gemini.edu
Author: ncomeau
Author-email: ncomeau@gemini.edu
License: MIT
Keywords: Gemini NIFS nifs pipeline reduction data IRAF iraf PYRAF pyraf astronomy integral field spectroscopy ifs ifu
Platform: UNKNOWN
Classifier: Development Status :: 4 - Beta
Classifier: Environment :: MacOS X
Classifier: Intended Audience :: Science/Research
Classifier: Intended Audience :: Education
Classifier: License :: OSI Approved :: MIT License
Classifier: Operating System :: MacOS
Classifier: Programming Language :: Python :: 2.7
Classifier: Topic :: Scientific/Engineering :: Astronomy
Classifier: Topic :: Scientific/Engineering :: Physics
Requires-Python: ~=2.7
